sqlalchemy_memory/__init__.py
sqlalchemy_memory/logger.py
sqlalchemy_memory/asyncio/__init__.py
sqlalchemy_memory/asyncio/dialect.py
sqlalchemy_memory/asyncio/session.py
sqlalchemy_memory/base/__init__.py
sqlalchemy_memory/base/connection.py
sqlalchemy_memory/base/dialect.py
sqlalchemy_memory/base/indexes.py
sqlalchemy_memory/base/pending_changes.py
sqlalchemy_memory/base/query.py
sqlalchemy_memory/base/session.py
sqlalchemy_memory/base/store.py
sqlalchemy_memory/base/resolvers/__init__.py
sqlalchemy_memory/base/resolvers/abstract.py
sqlalchemy_memory/base/resolvers/date.py
sqlalchemy_memory/base/resolvers/json_extract.py
sqlalchemy_memory/helpers/ordered_set.py
sqlalchemy_memory/helpers/utils.py
sqlalchemy_memory-0.4.0.dist-info/licenses/LICENSE
sqlalchemy_memory-0.4.0.dist-info/METADATA
sqlalchemy_memory-0.4.0.dist-info/WHEEL
sqlalchemy_memory-0.4.0.dist-info/entry_points.txt
sqlalchemy_memory-0.4.0.dist-info/top_level.txt
sqlalchemy_memory-0.4.0.dist-info/RECORD
