Metadata-Version: 2.4
Name: sqlalchemy-memory
Version: 0.4.0
Summary: In-memory SQLAlchemy 2.0 dialect for blazing‑fast prototyping.
Author: Mickael Burguet
License: MIT
Project-URL: Homepage, https://github.com/rundef/sqlalchemy-memory
Project-URL: Repository, https://github.com/rundef/sqlalchemy-memory
Project-URL: Issues, https://github.com/rundef/sqlalchemy-memory/issues
Keywords: sqlalchemy,in-memory database,memory store,prototype,testing,python orm,sqlalchemy dialect,sqlite alternative,lightweight database
Classifier: Development Status :: 4 - Beta
Classifier: Intended Audience :: Developers
Classifier: License :: OSI Approved :: MIT License
Classifier: Operating System :: OS Independent
Classifier: Programming Language :: Python
Classifier: Programming Language :: Python :: 3
Classifier: Programming Language :: Python :: 3.8
Classifier: Programming Language :: Python :: 3.9
Classifier: Programming Language :: Python :: 3.10
Classifier: Programming Language :: Python :: 3.11
Classifier: Programming Language :: Python :: 3.12
Classifier: Programming Language :: Python :: 3.13
Classifier: Topic :: Database :: Front-Ends
Classifier: Topic :: Software Development :: Libraries
Requires-Python: >=3.8
License-File: LICENSE
Requires-Dist: sqlalchemy<3.0,>=2.0
Requires-Dist: sortedcontainers>=2.4.0
Dynamic: license-file
